pyotrs/__init__.py
pyotrs/lib.py
pyotrs/version.py
pyotrs-1.4.0.dist-info/LICENSE
pyotrs-1.4.0.dist-info/METADATA
pyotrs-1.4.0.dist-info/WHEEL
pyotrs-1.4.0.dist-info/entry_points.txt
pyotrs-1.4.0.dist-info/RECORD
