Metadata-Version: 2.1
Name: pyotrs
Version: 1.4.0
Summary: Python wrapper for OTRS (using REST API)
Home-page: https://gitlab.com/rhab/PyOTRS
License: MIT
Author: Robert Habermann
Author-email: mail@rhab.de
Maintainer: Robert Habermann
Maintainer-email: mail@rhab.de
Requires-Python: >=3.8.1,<3.13
Classifier: Development Status :: 4 - Beta
Classifier: Environment :: Console
Classifier: Environment :: Web Environment
Classifier: Framework :: Pytest
Classifier: Framework :: Sphinx
Classifier: Intended Audience :: Developers
Classifier: Intended Audience :: System Administrators
Classifier: License :: OSI Approved :: MIT License
Classifier: Operating System :: POSIX :: Linux
Classifier: Programming Language :: Python :: 3
Classifier: Programming Language :: Python :: 3.9
Classifier: Programming Language :: Python :: 3.10
Classifier: Programming Language :: Python :: 3.11
Classifier: Programming Language :: Python :: 3.12
Classifier: Programming Language :: Python :: 3.8
Classifier: Topic :: Documentation :: Sphinx
Provides-Extra: cli
Requires-Dist: click (>=7.0) ; extra == "cli"
Requires-Dist: colorama (>=0.4.1) ; extra == "cli"
Requires-Dist: deprecation (>=2.1.0,<3.0.0)
Requires-Dist: requests (>=2.21.0)
Project-URL: Repository, https://gitlab.com/rhab/PyOTRS
